{
    "id": "cn.kuick.deal.marketing:interactive:c2",
    "type": "Module",
    "name": "交互管理",
    "description": "交互管理，ID范围：110100-111900",
    "menus": [
        {
            "id": "10000",
            "type": "Menu",
            "name": "运营管理",
            "description": "运营管理",
            "children": [
                {
                    "id": "10100",
                    "type": "MenuItem",
                    "name": "交互管理",
                    "description": "交互管理",
                    "children": []
                }
            ]
        }
    ],
    "children":[
        {
            "id": "110100",
            "type": "Button",
            "name": "创建文章",
            "description": "创建文章",
            "children": []
        },
        {
            "id": "110200",
            "type": "Button",
            "name": "创建多图文",
            "description": "创建文章",
            "children": []
        },
        {
            "id": "110400",
            "type": "Button",
            "name": "创建社交图片",
            "description": "创建社交图片",
            "children": []
        },
        {
            "id": "110500",
            "type": "Button",
            "name": "上传文件",
            "description": "上传文件",
            "children": []
        },
        {
            "id": "110700",
            "type": "Button",
            "name": "公众号群发",
            "description": "公众号群发",
            "children": []
        },
        {
            "id": "110800",
            "type": "Button",
            "name": "公众号自动推送",
            "description": "公众号自动推送",
            "children": []
        },
        {
            "id": "110900",
            "type": "Button",
            "name": "活动二维码",
            "description": "活动二维码",
            "children": []
        },
        {
            "id": "111000",
            "type": "Button",
            "name": "粉丝推广计划",
            "description": "粉丝推广计划",
            "children": []
        }
    ]
}